fishnet_cod/__init__.py
fishnet_cod/api/.pytest_cache/.gitignore
fishnet_cod/api/.pytest_cache/CACHEDIR.TAG
fishnet_cod/api/.pytest_cache/README.md
fishnet_cod/api/Dockerfile
fishnet_cod/api/__init__.py
fishnet_cod/api/api_model.py
fishnet_cod/api/controllers.py
fishnet_cod/api/main.py
fishnet_cod/api/routers/__init__.py
fishnet_cod/api/routers/datasets.py
fishnet_cod/api/routers/permissions.py
fishnet_cod/api/routers/timeseries.py
fishnet_cod/api/routers/users.py
fishnet_cod/api/utils.py
fishnet_cod/core/__init__.py
fishnet_cod/core/conf.py
fishnet_cod/core/model.py
fishnet_cod/core/session.py
fishnet_cod/core/version.py
fishnet_cod/executor/__init__.py
fishnet_cod/local_listener/Dockerfile
fishnet_cod/local_listener/__init__.py
fishnet_cod/local_listener/__main__.py
fishnet_cod/py.typed
fishnet_cod-1.2.0.dist-info/LICENSE
fishnet_cod-1.2.0.dist-info/METADATA
fishnet_cod-1.2.0.dist-info/WHEEL
fishnet_cod-1.2.0.dist-info/RECORD
